[
    {
        "key": "dbln",
        "value": "%7B%2261556643209332%22%3A%229FgS5cFI%22%2C%22100081152454222%22%3A%22t12qINAi%22%7D",
        "domain": "facebook.com",
        "path": "/login/device-based/",
        "hostOnly": false,
        "creation": "2024-04-29T23:17:16.518Z",
        "lastAccessed": "2024-04-29T23:17:16.519Z"
    },
    {
        "key": "datr",
        "value": "LSX3ZbgJqVNERx4V8-oWGjGs",
        "domain": "facebook.com",
        "path": "/",
        "hostOnly": false,
        "creation": "2024-04-29T23:17:16.519Z",
        "lastAccessed": "2024-04-29T23:17:16.519Z"
    },
    {
        "key": "sb",
        "value": "LSX3ZTYeqTY7ySq_NEqWO1Ya",
        "domain": "facebook.com",
        "path": "/",
        "hostOnly": false,
        "creation": "2024-04-29T23:17:16.519Z",
        "lastAccessed": "2024-04-29T23:17:16.519Z"
    },
    {
        "key": "ps_n",
        "value": "1",
        "domain": "facebook.com",
        "path": "/",
        "hostOnly": false,
        "creation": "2024-04-29T23:17:16.519Z",
        "lastAccessed": "2024-04-29T23:17:16.519Z"
    },
    {
        "key": "ps_l",
        "value": "1",
        "domain": "facebook.com",
        "path": "/",
        "hostOnly": false,
        "creation": "2024-04-29T23:17:16.519Z",
        "lastAccessed": "2024-04-29T23:17:16.519Z"
    },
    {
        "key": "dpr",
        "value": "2.1988937854766846",
        "domain": "facebook.com",
        "path": "/",
        "hostOnly": false,
        "creation": "2024-04-29T23:17:16.519Z",
        "lastAccessed": "2024-04-29T23:17:16.519Z"
    },
    {
        "key": "locale",
        "value": "en_US",
        "domain": "facebook.com",
        "path": "/",
        "hostOnly": false,
        "creation": "2024-04-29T23:17:16.519Z",
        "lastAccessed": "2024-04-29T23:17:16.519Z"
    },
    {
        "key": "vpd",
        "value": "v1%3B665x360x2",
        "domain": "facebook.com",
        "path": "/",
        "hostOnly": false,
        "creation": "2024-04-29T23:17:16.519Z",
        "lastAccessed": "2024-04-29T23:17:16.519Z"
    },
    {
        "key": "m_pixel_ratio",
        "value": "2",
        "domain": "facebook.com",
        "path": "/",
        "hostOnly": false,
        "creation": "2024-04-29T23:17:16.519Z",
        "lastAccessed": "2024-04-29T23:17:16.519Z"
    },
    {
        "key": "wd",
        "value": "360x665",
        "domain": "facebook.com",
        "path": "/",
        "hostOnly": false,
        "creation": "2024-04-29T23:17:16.519Z",
        "lastAccessed": "2024-04-29T23:17:16.519Z"
    },
    {
        "key": "c_user",
        "value": "61558724290849",
        "domain": "facebook.com",
        "path": "/",
        "hostOnly": false,
        "creation": "2024-04-29T23:17:16.519Z",
        "lastAccessed": "2024-04-29T23:17:16.519Z"
    },
    {
        "key": "xs",
        "value": "9%3AeVt8-TQw5uBUtA%3A2%3A1714432614%3A-1%3A-1",
        "domain": "facebook.com",
        "path": "/",
        "hostOnly": false,
        "creation": "2024-04-29T23:17:16.519Z",
        "lastAccessed": "2024-04-29T23:17:16.519Z"
    },
    {
        "key": "fr",
        "value": "1IAkIcr9VUmjZMcUj.AWWhfQUblCBWo9n2D0Hf-SC83lY.BmLCU2..AAA.0.0.BmMCpo.AWVUiagzpMc",
        "domain": "facebook.com",
        "path": "/",
        "hostOnly": false,
        "creation": "2024-04-29T23:17:16.519Z",
        "lastAccessed": "2024-04-29T23:17:16.519Z"
    },
    {
        "key": "fbl_st",
        "value": "101623165%3BT%3A28573876",
        "domain": "facebook.com",
        "path": "/",
        "hostOnly": false,
        "creation": "2024-04-29T23:17:16.519Z",
        "lastAccessed": "2024-04-29T23:17:16.519Z"
    },
    {
        "key": "wl_cbv",
        "value": "v2%3Bclient_version%3A2482%3Btimestamp%3A1714432617",
        "domain": "facebook.com",
        "path": "/",
        "hostOnly": false,
        "creation": "2024-04-29T23:17:16.519Z",
        "lastAccessed": "2024-04-29T23:17:16.519Z"
    }
]
